{
  "coffees": [{
          "id":"001",
          "name": "Affogato",
          "description": "This is a term that literally means 'drowned'. It is the description of a shot of separately served espresso that is later poured over a the top of a scoop of vanilla ice cream or gelato. This beverage is usually served in a short drink glass and is a Italian desert favourite. Popular Affogatos include Vanilla Affogato, Mocha Affogato, and Peppermint Affogato.",
          "category": "americano",
          "image":"https://lh3.googleusercontent.com/AgxJK8PpRTmMFDFUAczKIblhzlwC3D4rxNeDQ7N5Nh2xZDEJnwjd3fNQvO3XsaQVzRNUUw=s128",
          "prices": {
            "small": 2,
            "medium": 3,
            "large": 5
          },
          "favorite" : "false"
      },
      {
          "id":"002",
          "name": "Americano",
          "description": "Also known as 'Lungo' or 'Long Black' and made by diluting 1-2 shots of espresso with hot water in order to approximate the texture, flavor and body of an American-style drip coffee. Said to have been originally devised as a sort of insult to Americans who wanted their Italian espresso diluted.",
          "category": "americano",
          "image":"https://lh3.googleusercontent.com/N2j-r5eEE9Xtv_R3s0JhAZaqRucd3X45jn0sKp5YG0HMiJkVN7VotqMjEatMp3WYyEni=s85",
          "prices": {
            "small": 2,
            "medium": 3,
            "large": 5
          },
          "favorite" : "false"

      }, {
        "id":"003",
          "name": "Babycino",
          "description": "A cappuccino styled drink served in an up-market café typically for children. It consists of warm milk in a small cup and topped with milk froth and chocolate powder. No espresso coffee essence is added.",
          "category": "cappuccino",
          "image":"https://lh3.googleusercontent.com/O31wwDqOOGsaTvywRcMKjdZfHRbw5R6vgeKkM5uPiFYmqPl1FIZ6dyTn5E-ajDUvMvHWFw=s128",
          "prices": {
            "small": 2,
            "medium": 3,
            "large": 5
          },
          "favorite" : "false"

      }, {
          "id":"004",
          "name": "Breve",
          "description": "A term in Italian that means short and is used to describe an espresso coffee drink made with a half-and-half light cream or semi-skim milk instead of full fat milk",
          "category": null,
          "image":"https://lh3.googleusercontent.com/42nsQlVv1TTmK7VZ9EGqrcq7014L1Gqev3BbCmLwca26Rln1q8NqwpUnlIBc4GnQcR6NRAQ=s85",
          "prices": {
            "small": 2,
            "medium": 3,
            "large": 5
          },
          "favorite" : "false"
      }, {
          "id":"005",
          "name": "Caffe' Freddo",
          "description": "Chilled, sweetened espresso served in a tall glass, often on ice",
          "category": "cocktail",
          "image": "https://lh3.googleusercontent.com/KKI-slMQL_SeyeMY74Ny5ihhRCz0CLEewICsOt5hVZYZGFdGgQ5c28uGopqXR7w3HDltFw=s128",
          "prices": {
            "small": 2,
            "medium": 3,
            "large": 5
          },
          "favorite" : "false"

      }, {
          "id":"006",
          "name": "Caffe Latte or “Latte”",
          "description": "A ‘premium milk coffee experience’. Freshly steamed milk without foam served in a tall glass with a shot of espresso coffee.",
          "category": "latte",
          "image": "https://lh3.googleusercontent.com/8a_CL5zx2Vvb6ky8d_XTouNH6s9W-8KM0wTdsNc1UAwF5ZUWbYAWyr9DnW3VESJZ_nMU8ok=s128",
          "prices": {
            "small": 2,
            "medium": 3,
            "large": 5
          },
          "favorite" : "false"

      }, {
          "id":"007",
          "name": "Caffe Mocha",
          "description": "A combination of chocolate syrup and a shot of espresso, topped with steamed milk and a layer of micro-foam. Finished with a sprinkled of chocolate.",
          "category": null,
          "image": "https://lh3.googleusercontent.com/Usvbclybu_g9K814brWKKJ_2Rzonno0TMqdi8jANNQNrnD2daAEPxuZBjMT2MT2PTyjG44g=s85",
          "prices": {
            "small": 2,
            "medium": 3,
            "large": 5
          },
          "favorite" : "false"

      }, {
          "id":"008",
          "name": "Cappuccino Chiaro",
          "description": "(AKA Wet or Light cappuccino): Cappuccino prepared with more milk than usual.",
          "category": "cappuccino",
          "image": "https://lh3.googleusercontent.com/KilCV32b0zTVxqCfm2SaM7HuA48H3QmpSisFNFG88Cnpj5SK7SQ44swyMo1eMPeP3pkCcP8=s85",
          "prices": {
            "small": 2,
            "medium": 3,
            "large": 5
          },
          "favorite" : "false"
      },
      {
          "id":"009",
          "name": "Cappuccino Scuro",
          "description": "(AKA Dry or Dark cappuccino) Cappuccino prepared with less milk than usual.",
          "category": "cappuccino",
          "image": "https://lh3.googleusercontent.com/uetFXqqhTBX5o0gnHJ7x4D9IzrLFdKzKqjXbPzbsUVYTiGXZUMMOlRoZbZJaOV3zCY5mFQ=s113",
          "prices": {
            "small": 2,
            "medium": 3,
            "large": 5
          },
          "favorite" : "false"
      },
      {
          "id":"010",
          "name": "Cappuccino",
          "description": "A ‘traditional morning heart starter’. Steamed foamed velvety milk poured over one shot (1) of coffee oil extract made from 12gm of freshly ground beans producing 38ml of essence. Finished by topping with foam and a sprinkle of chocolate powder. Served in a pre heated vitrified ceramic cup.",
          "category": "cappuccino",
          "image": "https://lh3.googleusercontent.com/9flj2fq-8XTN0OOZ6LUoOSqKuQHfdx4xgNeHBeNyr2eDfdD46DqX-1qNizAdsyK-Ynnxmg=s128",
          "prices": {
            "small": 2,
            "medium": 3,
            "large": 5
          },
          "favorite" : "false"
      },
      {
        "id":"011",
          "name": "Con panna",
          "description": " Like the beverage 'macchiato', but whipped cream is substituted for steamed milk.",
          "category": "espresso",
          "image": "https://lh3.googleusercontent.com/MvZl44BKIr_qEobdWzJstiuQQ0Hmb8hJK2pqY5qeuApbXSMGZlOX6kyiszl5OyB1VsTP=s85",
          "prices": {
            "small": 2,
            "medium": 3,
            "large": 5
          },
          "favorite" : "false"
      },
      {
          "id":"012",
          "name": "Cortado",
          "description": "means 'cut' in Spanish so the double shot espresso served in a demetesse glass supported with a metal handle is 'cut' with an equal part of hot milk, making it in between the size and strength of a macchiato and a cappuccino. It is popular in Spain and Portugal, as well as throughout Latin America and Cuba, where it is drunk in the afternoon. Variations include more froth on top than a traditional cortado and occasionally with different names such as Piccolo or Gibraltar. Thanks to Ryan Cerbus for the entry.",
          "category": "espresso",
          "image": "https://lh3.googleusercontent.com/k0x-wWIXIa_jZBPMTtgnqEc0OsEQDBHppgOrhU8Jbr-UEb4noLljvAqRYD8RLn9HQF9uNA=s128",
          "prices": {
            "small": 2,
            "medium": 3,
            "large": 5
          },
          "favorite" : "false"
      },
      {
          "id":"013",
          "name": "Corretto",
          "description": "Espresso 'corrected' with a touch of grappa, cognac, sambuca, or other spirit.",
          "category": "espresso",
          "image": "https://lh3.googleusercontent.com/CooXYxlWVZojQdHBmxhgzXT1LcGmznd_qCFTWI2lFRG76QDNBZYBHOxkFnit0I8O893Tljs=s119",
          "prices": {
            "small": 2,
            "medium": 3,
            "large": 5
          },
          "favorite" : "false"
      },
      {
          "id":"014",
          "name": "Bicerin",
          "description": "a traditional hot drink native to Turin, Italy, made of espresso, drinking chocolate and whole milk. Everybody I know who knows it learned about it from Carluccio's http://www.carluccios.com/",
          "category": "espresso",
          "image": "https://lh3.googleusercontent.com/OWtNijDFSwzK39f9GaqrKweOQUVdi7UxcM0U19ZjjjKou0EG6QSg9DQnTfpQlIYgWVQTqw=s128",
          "prices": {
            "small": 2,
            "medium": 3,
            "large": 5
          },
          "favorite" : "false"
      },
      {
          "id":"015",
          "name": "Ethiopian Coffee",
          "description": "beans roasted in the presence of the drinkers immediately prior to brewing, very coarsely ground by hand in a mortar and pestle",
          "category": null,
          "image": "https://lh3.googleusercontent.com/OkW_ozgf8tdVvMCj80I3c8rR9MJ5hk9A9gG3IDpJ1yvh0T1AVrO8VojkU1sTaUfe-pHnxQ=s119",
          "prices": {
            "small": 2,
            "medium": 3,
            "large": 5
          },
          "favorite" : "false"
      },
      {
          "id":"016",
          "name": "White coffee",
          "description": "A black coffee with added milk.this good types of coffee",
          "category": "white",
          "image": "https://lh3.googleusercontent.com/RmmxVomlsyMhfAsJK6QeeiB-9efYNrbrAl0v4lnpHBTUrPngVUOHqHgwtpt5sjCGKh4vCfY=s170",
          "prices": {
            "small": 2,
            "medium": 3,
            "large": 5
          },
          "favorite" : "false"
      },
      {
          "id":"017",
          "name": "Frappe",
          "description": "Popular in parts of Europe and Latin America, especially during the summer months. Originally it was a cold espresso, but it has more recently been prepared by putting 1-2 teaspoons of instant coffee with sugar, water and ice. The drink is served in a long glass.this good types of coffee",
          "category": "frappe",
          "image": "https://lh3.googleusercontent.com/GRcoV8aeA82Yek5t-WJ_2pzbmPGPNUXZQKY750sqY_ekreEgnvNbgBs0NG6dsx-AqcjF=s147",
          "prices": {
            "small": 2,
            "medium": 3,
            "large": 5
          },
          "favorite" : "false"
      },
      {
          "id":"018",
          "name": "Vietnamese style coffee",
          "description": "A drink made by dripping hot water though a metal mesh, with the intense brew then poured over ice and sweetened, condensed milk. This process uses a lot more coffee grounds and is thus a lot slower than most kinds of brewing.this good types of coffee",
          "category": null,
          "image": "https://lh3.googleusercontent.com/ENsbn6d7Mb8L7MFqSDsrjkiZCfY6Be-N2-UrInu57GczJUZJm45TaqFZzvOqx80SdchFyA=s102",
          "prices": {
            "small": 2,
            "medium": 3,
            "large": 5
          },
          "favorite" : "false"
      },
      {
          "id":"019",
          "name": "Turkish Coffee",
          "description": "Made by boiling finely ground coffee and water together to form a muddy, thick coffee mix. In fact, the strongest Turkish coffee can almost keep a spoon standing upright. It’s often made in what’s known as an Ibrik, a long-handled, open, brass or copper pot. It is then poured, unfiltered, into tiny Demitasse cups, with the fine grounds included. It’s then left to settle for a while before serving, with sugar and spices often added to the cup.this good types of coffee",
          "category": null,
          "image": "https://lh3.googleusercontent.com/55_aVkn324Tv5VNrLp2PjiN2JaNcaMeQXe02mOJY1HrjNQvHRiMOHktcRItOmIQ0fY_J=s85",
          "prices": {
            "small": 2,
            "medium": 3,
            "large": 5
          },
          "favorite" : "false"
      },
      {
          "id":"020",
          "name": "Flat White Coffee",
          "description": " “White Coffee” - ‘uncompromising taste’.Steamed microfroam milk poured through and under the espresso crème produced from one shot (1) of coffee extract made on 12gm of freshly ground coffee producing 38ml of essence. Served in a pre heated vitrified ceramic cup. A common espresso coffee order in Australia/New Zealand. Great for latte art!",
          "category": "white",
          "image": "https://lh3.googleusercontent.com/aQ9WN7VJh4wVYkjgzonyQsvObIaKA4yF0Z1fwkp6ExoHuOCr362Evp0Qru3yYzYETKrz=s116",
          "prices": {
            "small": 2,
            "medium": 3,
            "large": 5
          },
          "favorite" : "false"
      },
      {
          "id":"021",
          "name": "Hammerhead",
          "description": "A coffee drink only served in the USA. It is an American term for a shot of espresso in a coffee cup that is topped up with drip-filtered coffee. As Kris Rosvold explains in the comments: In Oregon, the hammerhead is usually known as a red eye and uses 2 shots of espresso topped up in a 16oz travel mug with drip coffee. It's also sometimes called a 'shot in the dark'.",
          "category": null,
          "image":"https://lh3.googleusercontent.com/UCTVWWOvClZe77fLTvfl5vCEUewKs3wkrdGvmcRgoBlPtXREkkrUvxrsCgd7I5PuDhM1jA=s128",
          "prices": {
            "small": 2,
            "medium": 3,
            "large": 5
          },
          "favorite" : "false"
      },
      {
          "id":"022",
          "name": "Irish Coffee",
          "description": "Coffee mixed with a dash of Irish whiskey and served with cream on top.",
          "category": null,
          "image": "https://lh3.googleusercontent.com/vrMeBwbOnEF_ReNjYQOt2fApmCdQ2YZaOEulloS0XFvaQPl29K8pHmSvt8_fl84oAA0gNw=s85",
          "prices": {
            "small": 2,
            "medium": 3,
            "large": 5
          },
          "favorite" : "false"
      },
      {
          "id":"023",
          "name": "Macchiato",
          "description": "Meaning “stained” - Described as ‘strong, marked or stained’. A touch of steamed foamed milk added to a double shot of coffee extract made from 24gm of fresh ground beans producing 75ml of essence. Served in glass.",
          "category": "macchiato",
          "image": "https://lh3.googleusercontent.com/E9WdXGBYmjFiMH3DcYdzfEN0XFXDHK-fx1Q2pdbtwYBRwJXAsNMfi5l7b9UK4DTocWkwwkg=s113",
          "prices": {
            "small": 2,
            "medium": 3,
            "large": 5
          },
          "favorite" : "false"
      },
      {
          "id":"024",
          "name": "Mazagran",
          "description": "A French drink composed of cold coffee and seltzer water. First created by the French soldiers in 1840 in the town of Argelia. A variation includes iced coffee made with maraschino.",
          "category": null,
          "image": "https://lh3.googleusercontent.com/EvdJqSoeS-T0FyfEKEpE0s_BEpe8XdO9gzck8VIZbOCdii-pgT1Q6XI33gZgu1kljCrBb_s=s85",
          "prices": {
            "small": 2,
            "medium": 3,
            "large": 5
          },
          "favorite" : "false"
      },
      {
          "id":"025",
          "name": "Quad",
          "description": " An espresso drink made with four shots of coffee.",
          "category": "espresso",
          "image": "https://lh3.googleusercontent.com/DzPmvQiH0zCuh9MtrcsNOH-lwViwxgxYzv9cgwORfA9l8expqkO1ngOBzr-n1xDSA7Lq=s140",
          "prices": {
            "small": 2,
            "medium": 3,
            "large": 5
          },
          "favorite" : "false"
      },
      {
          "id":"026",
          "name": "Ristretto",
          "description": "(Ristretto in Italian means 'restricted, shrunk or short') It is the richest and most concentrated espresso drink where less water but the same amount of coffee is used to make the beverage and creates a less bitter espresso. The extraction time is shortened producing as little as 3 oz of liquid per serving. Pure and intense espresso served in a demitasse cup.",
          "category": null,
          "image": "https://lh3.googleusercontent.com/IeCAiGXO3759MxGJK_G8uKQGtMCq22k9haDNNZfy6v8ZanOUfItaMNZiELwhz4nyqMuu8A=s127",
          "prices": {
            "small": 2,
            "medium": 3,
            "large": 5
          },
          "favorite" : "false"
      },
      {
          "id":"027",
          "name": "Short Black",
          "description": "A ‘pure intense Italian favourite with a biting crème head. Contains 75ml of pure double shot (2) coffee essence made from 24gm of fresh ground coffee beans. Traditionally served in glass and is referred to as Espresso by European customers.",
          "category": null,
          "image": "https://lh3.googleusercontent.com/JJKuWLH_Q8yyAa4iqdCi8pufIE9-QyWYEHKo_9j1o0db-haqm_ksKc8f5_yV2hACTS1mYy8=s85",
          "prices": {
            "small": 2,
            "medium": 3,
            "large": 5
          },
          "favorite" : "false"
      },
      {
          "id":"028",
          "name": "Viennese Coffee",
          "description": "Brewed black coffee of any roast or origin topped and served with whipped cream.",
          "category": null,
          "image": "https://lh3.googleusercontent.com/NxWPcTmcPp-jpYAIikylCbHdMHWQw9KkLB9155rVQokO4-TQm4mhDH2nGoDuHwtIWJJ9aA=s96",
          "prices": {
            "small": 2,
            "medium": 3,
            "large": 5
          },
          "favorite" : "false"
      },
      {
          "id":"029",
          "name": "Latte Macchiato",
          "description": " Steamed milk served in a tall glass rather than a cup that is “stained” by a shot of espresso coffee.",
          "category": "macchiato",
          "image": "https://lh3.googleusercontent.com/tMl8lr1z73mmaOvFBcxmwftpwSc9myEw6yp_rBiNm8gA3QNOVpFMSqzehXaqNYmfN7ztsLU=s104",
          "prices": {
            "small": 2,
            "medium": 3,
            "large": 5
          },
          "favorite" : "false"
      },
      {
          "id":"030",
          "name": "Long Black",
          "description": "Often called the “American”. It is the ‘benchmark coffee without milk’. It is pure coffee made from one & one half shots of coffee extract made on 16gm of fresh ground beans producing 50ml of essence blended with steamed water. Served in a pre heated vitrified ceramic cup with the essence floated over the top of a cup filled with hot/boiling water. It is a standard espresso (Short Black) but lengthened by the addition of hot/boiling water.",
          "category": null,
          "image": "https://lh3.googleusercontent.com/UsPk0wFIuXsyEf0XD7virxspWeHuHYE-duguAqiNxPDLJYB5biVeYN1JzMaUBuP_XUErKA=s88",
          "prices": {
            "small": 2,
            "medium": 3,
            "large": 5
          },
          "favorite" : "false"
      },
      {
          "id":"031",
          "name": "Lungo",
          "description": "An espresso made by purposely allowing more water to flow through the ground coffee than usual. (sometimes called an Americano or ‘long’).",
          "category": "cocktail",
          "image": "https://lh3.googleusercontent.com/n9B1xT4RJVea8X1uqRxhF0hkO1CA5a1ookiFwau-JriBk23ThJ-YD_g2RtnvnMTOSKUFKg=s85",
          "prices": {
            "small": 2,
            "medium": 3,
            "large": 5
          },
          "favorite" : "false"
      },
      {
          "id":"032",
          "name": "Doppio",
          "description": " Italian term for double. Double Espresso or twice the amount of coffee and twice the amount of water. Basically it describes two shots of espresso in one demitasse container.",
          "category": "espresso",
          "image": "https://lh3.googleusercontent.com/-BSG9lOdIbHD0HTiwzMnMrMJt7-q8-fDoujW87WR0NRJpE8wuLeFWlseYNGffEqjrEBk=s85",
          "prices": {
            "small": 2,
            "medium": 3,
            "large": 5
          },
          "favorite" : "false"
      },
      {
          "id":"033",
          "name": "Espresso con Panna",
          "description": "American term where a shot is extracted longer for a bit of extra espresso. Tends to maximizes the caffeine but will mostly produce a more bitter cup.",
          "category": "espresso",
          "image": "https://lh3.googleusercontent.com/ctZo_XFAQJdiaDpXcxyCOPquDnIM3EcLo9Qzn2pu94pHUuS3GxuqL4gCa7UQn3_w3D6U=s85",
          "prices": {
            "small": 2,
            "medium": 3,
            "large": 5
          },
          "favorite" : "false"
      },
      {
          "id":"034",
          "name": "Espresso Romano",
          "description": "Espresso served with a lemon peel on the side. Whilst not a typical accompaniment in Italy it is commonly served with the espresso beverage in America",
          "category": "espresso",
          "image": "https://lh3.googleusercontent.com/ibH2YP6M-hu3OXuqrMr1efhW9oEk0pJA0OF1T02zvykyuS4xzHAsSm15xguSLLT-L49C=s128",
          "prices": {
              "small": 2,
              "medium": 3,
              "large": 5
          },
          "favorite" : "false"
      },
      {
          "id":"035",
          "name": "Caffe Latte",
          "description": "Our dark, rich espresso balanced with steamed milk and a light layer of foam. A perfect milk forward warm up.",
          "category": "latte",
          "image": "https://lh3.googleusercontent.com/y_vZCmT_htuQ6kb4xmpfmGdQQKVwa_SmctDevVqlghpRjRBM6xD-kM6iETmQAtXDzwnC=s113",
          "prices": {
              "small": 2.95,
              "medium": 3.65,
              "large": 4.15
          },
          "favorite" : "false"
      },
      {
          "id":"036",
          "name": "Caffe Mocha",
          "description": "We combine our rich, full-bodied espresso with bittersweet mocha sauce and steamed milk, then top it off with sweetened whipped cream. The classic coffee drink to satisfy your sweet tooth.",
          "category": "cocktail",
          "image": "https://lh3.googleusercontent.com/vNQyNrswXlsuryuudNNegvZx2z6vh5f0bu7PQiQlLrz4TGaPUIVAQ31uiEeBKW_JtklNog=s85",
          "prices": {
              "small": 3.45,
              "medium": 4.15,
              "large": 4.65
          },
          "favorite" : "false"
      },
      {
          "id":"037",
          "name": "White Chocolate Mocha",
          "description": "Our signature espresso meets white chocolate sauce and steamed milk, then is finished off with sweetened whipped cream in this white chocolate delight.",
          "category": "cocktail",
          "image": "https://lh3.googleusercontent.com/9m2K09bReGRYH0JZ5y_UKtQYnC4yW1H_01Yq6tUs1vdRBaX2CHhlYDnxIyJ5wn6W-g3qLQ=s85",
          "prices": {
              "small": 3.75,
              "medium": 4.45,
              "large": 4.75
          },
          "favorite" : "false"
      },
      {
          "id":"038",
          "name": "Freshly Brewed Coffee",
          "description": "With subtle notes of cocoa and toasted nuts, enjoy a smooth, balanced and rich blend of Latin American coffees made perfectly into one.",
          "category": "cocktail",
          "image": "https://lh3.googleusercontent.com/S7ZkwGKVQcEkYYKIBR5iG84bXo9VHSzq6tKZ-Q8w3JkFjFRfR97pSDFb3zA1oaeF9f5hxg=s128",
          "prices": {
              "small": 1.85,
              "medium": 2.10,
              "large": 2.45
          },
          "favorite" : "false"
      },
      {
          "id":"039",
          "name": "Cinnamon Dolce Latte",
          "description": "With subtle notes of cocoa and toasted nuts, enjoy a smooth, balanced and rich blend of Latin American coffees made perfectly into one.",
          "category": "latte",
          "image": "",
          "prices": {
              "small": 3.65,
              "medium": 4.25,
              "large": 4.65
          },
          "favorite" : "false"
      },
      {
          "id":"040",
          "name": "Cinnamon Dolce Latte",
          "description": "We add freshly steamed milk and cinnamon dolce flavored syrup to our classic espresso, then top it off with sweetened whipped cream and cinnamon dolce topping. You're in for a treat.",
          "category": "latte",
          "image": "https://lh3.googleusercontent.com/tLm7gW6vv7JXNeqZ4K0-denSY00R128NIxiigdJju8GFvb97tDOt4HQNyswbhr50lnM4=s85",
          "prices": {
              "small": 3.65,
              "medium": 4.25,
              "large": 4.65
          },
          "favorite" : "false"
      },
      {
          "id":"041",
          "name": "Skinny Vanilla Latte",
          "description": "Espresso, steamed nonfat milk and a sugar-free flavored syrup.",
          "category": "latte",
          "image": "https://lh3.googleusercontent.com/OCqNhWy4RT67kJg7v0NxXHmV3FRYpQ_xNACt0xD3pN_4cn1-_-hfD_Tuk5UUU9m1WicICA=s85",
          "prices": {
              "small": 3.45,
              "medium": 4.15,
              "large": 4.65
          },
          "favorite" : "false"
      },
      {
          "id":"042",
          "name": "Caramel Macchiato",
          "description": "Freshly steamed milk with vanilla-flavored syrup is marked with espresso and topped with caramel drizzle for an oh-so-sweet finish.",
          "category": "cocktail",
          "image": "https://lh3.googleusercontent.com/wPc8EeJcLeMr92gvDNMZxlWOLO9TC3R4RqUQPXK7bbs9FPGG5FPcTE0rNrvrQ-izhkN5=s85",
          "prices": {
              "small": 3.75,
              "medium": 4.45,
              "large": 4.75
          },
          "favorite" : "false"
      },
      {
          "id":"043",
          "name": "Teavana® Oprah Cinnamon Chai Tea Latte",
          "description": "This distinctive chai blend features a bold infusion of cinnamon, ginger, cardamom and cloves, blended with loose-leaf black tea and rooibos. Lightly sweetened and finished with steamed milk.",
          "category": "latte",
          "image": "https://lh3.googleusercontent.com/SIOYEOv-bgtf86wFQuLmvaF9ZFNAPOnNKTeUCmF-SiFdE4ORw3XMKZri6qiRdyuSwSL2Sw=s85",
          "prices": {
              "small": 3.65,
              "medium": 4.25,
              "large": 4.65
          },
          "favorite" : "false"
      },
      {
          "id":"044",
          "name": "Caramel Flan Latte",
          "description": "We add freshly steamed milk and cinnamon dolce flavored syrup to our classic espresso, then top it off with sweetened whipped cream and cinnamon dolce topping. You're in for a treat.",
          "category": "latte",
          "image": "https://lh3.googleusercontent.com/cXuI8ss4qUaT_iR5Q0c-b5AHHzT9VbtZU5mOPm9DhP4F5Wi2ztXLzUAkrHw8_xTXeT_aH84=s85",
          "prices": {
              "small": 3.75,
              "medium": 4.55,
              "large": 4.75
          },
          "favorite" : "false"
      },
      {
          "id":"045",
          "name": "Flat White",
          "description": "Bold ristretto shots of espresso get the perfect amount of steamed whole milk to create a not too strong, not too creamy, just right flavor.",
          "category": "cocktail",
          "image": "https://lh3.googleusercontent.com/1GYeIaMxjbdqrWSrQDXUnl4E6DpoIyHsk1MsMOibt9q5SJiGLuch6aELpJX5OkxG6QReyA=s85",
          "prices": {
              "small": 3.75,
              "medium": 4.55,
              "large": 4.75
          },
          "favorite" : "false"
      },
      {
          "id":"046",
          "name": "Cinnamon Dolce Latte",
          "description": "We add freshly steamed milk and cinnamon dolce flavored syrup to our classic espresso, then top it off with sweetened whipped cream and cinnamon dolce topping. You're in for a treat.",
          "category": "latte",
          "image": "https://lh3.googleusercontent.com/9oU6wjcGyIyhfw2l7ItZu5HieilOBnFEjvn7OjRKqBAeGop-scwjtOQpfyrJunmxQ37mOQ=s85",
          "prices": {
              "small": 3.65,
              "medium": 4.25,
              "large": 4.65
          },
          "favorite" : "false"
      },
      {
          "id":"047",
          "name": "Skinny Peppermint Mocha",
          "description": "A light and flavorful combination of espresso, creamy steamed nonfat milk, sugar-free mocha sauce and sugar-free peppermint syrup.",
          "category": "cocktail",
          "image": "https://lh3.googleusercontent.com/8oS8XvQpbDrU1vaNVKx5KyORLmbVo-X941u-0oDRqi60ic9F7mCMo8j92-QAVb8QMiFphA=s85",
          "prices": {
              "small": 3.95,
              "medium": 4.65,
              "large": 4.95
          },
          "favorite" : "false"
      },
      {
          "id":"048",
          "name": "Pumpkin Spice Latte",
          "description": "Our signature espresso and milk are highlighted by flavor notes of pumpkin, cinnamon, nutmeg and clove to create this incredible beverage that's a fall favorite. Enjoy it topped with whipped cream and real pumpkin pie spices.",
          "category": "latte",
          "image": "https://lh3.googleusercontent.com/CQUMKX9Big_q0_bB72P2PF0j4Hve5f-XjfDNWHOhkFvhYutnR2rfzlxYGcXKKW6iAEfCsA=s85",
          "prices": {
              "small": 4.25,
              "medium": 4.95,
              "large": 5.95
          },
          "favorite" : "false"
      },
      {
          "id":"049",
          "name": "Salted Caramel Mocha",
          "description": "Our signature espresso and milk are highlighted by flavor notes of pumpkin, cinnamon, nutmeg and clove to create this incredible beverage that's a fall favorite. Enjoy it topped with whipped cream and real pumpkin pie spices.",
          "category": "Starbucks",
          "image": "https://lh3.googleusercontent.com/B_IFlBr0elzaifRaeIPBTQRuY3_rXmGyIRW_LQlTqJUjvz7V80yY0MsDut099UxJKkZeUXE=s85",
          "prices": {
              "small": 4.25,
              "medium": 4.95,
              "large": 5.95
          },
          "favorite" : "false"
      },
      {
          "id":"050",
          "name": "Toasted Graham Latte",
          "description": "Graham and sweet cream meet steamed milk and our signature espresso, then are finished off with a sprinkling of cinnamon graham crumbles for a less sweet perfect treat.",
          "category": "latte",
          "image": "https://lh3.googleusercontent.com/DbVCzXcikhgh8KR_jypneNCxDdA8AvUas87U-RI7tEHod-pmcYxtkGWm8yp--tAOFAeq=s113",
          "prices": {
              "small": 4.25,
              "medium": 4.95,
              "large": 5.95
          },
          "favorite" : "false"
      }
  ]
}